{
  "DXDP": {
    "e": 886,
    "n": "Djangou",
    "mv": -1.56,
    "c": "Dapango",
    "runways": [
      {
        "s": "D",
        "l": 3921,
        "w": 82,
        "e1": {
          "n": "18",
          "h": 181
        },
        "e2": {
          "n": "36",
          "h": 1
        }
      }
    ]
  },
  "DXMG": {
    "e": 505,
    "n": "Sansanne-Mango",
    "mv": -1.6,
    "freqs": [
      {
        "t": "FSS",
        "f": 118.3,
        "n": "MANGO"
      }
    ],
    "runways": [
      {
        "s": "G",
        "l": 3979,
        "w": 139,
        "e1": {
          "n": "22",
          "h": 218
        },
        "e2": {
          "n": "04",
          "h": 38
        }
      }
    ]
  },
  "DXNG": {
    "e": 1507,
    "n": "Niamtougou Intl",
    "mv": -1.53,
    "c": "Niamtougou",
    "freqs": [
      {
        "t": "T",
        "f": 118.3,
        "n": "NIAMTOUGOU"
      },
      {
        "t": "T",
        "f": 118.8,
        "n": "NIAMTOUGOU"
      }
    ],
    "runways": [
      {
        "s": "A",
        "l": 8208,
        "w": 194,
        "e1": {
          "n": "21",
          "h": 204
        },
        "e2": {
          "n": "03",
          "h": 24
        }
      }
    ]
  },
  "DXKR": {
    "e": 912,
    "n": "Kara Airport",
    "mv": -1.53,
    "c": "Kara",
    "runways": [
      {
        "s": "D",
        "l": 3925,
        "w": 77,
        "e1": {
          "n": "16",
          "h": 157
        },
        "e2": {
          "n": "34",
          "h": 337
        }
      }
    ]
  },
  "DXSK": {
    "e": 1257,
    "n": "Sokode",
    "mv": -1.72,
    "freqs": [
      {
        "t": "FSS",
        "f": 118.1,
        "n": "SOKODE"
      }
    ],
    "runways": [
      {
        "s": "G",
        "l": 3337,
        "w": 184,
        "e1": {
          "n": "20",
          "h": 204
        },
        "e2": {
          "n": "02",
          "h": 24
        }
      }
    ]
  },
  "DXKA": {
    "e": 1069,
    "n": "Kpalime Airport",
    "mv": -2.32,
    "c": "Kpalime",
    "runways": [
      {
        "s": "G",
        "l": 2962,
        "w": 66,
        "e1": {
          "n": "12",
          "h": 115
        },
        "e2": {
          "n": "30",
          "h": 295
        }
      }
    ]
  },
  "DXAK": {
    "e": 689,
    "n": "Akpaka",
    "mv": -1.93,
    "c": "Atakpame",
    "runways": [
      {
        "s": "D",
        "l": 2844,
        "w": 220,
        "e1": {
          "n": "06",
          "h": 55
        },
        "e2": {
          "n": "24",
          "h": 235
        }
      }
    ]
  },
  "DXXX": {
    "e": 62,
    "n": "Tokoin",
    "mv": -2.18,
    "c": "Lome",
    "freqs": [
      {
        "t": "T",
        "f": 120.7,
        "n": "LOWE"
      }
    ],
    "runways": [
      {
        "s": "A",
        "l": 9856,
        "w": 144,
        "e1": {
          "n": "22",
          "h": 221
        },
        "e2": {
          "n": "04",
          "h": 41
        }
      }
    ]
  }
}