{
  "Y87": {
    "e": 933,
    "n": "Empire",
    "mv": -5.59,
    "freqs": [
      {
        "t": "MC",
        "f": 122.9,
        "n": "EMPIRE"
      },
      {
        "t": "CTAF",
        "f": 122.9,
        "n": "EMPIRE"
      }
    ],
    "runways": [
      {
        "s": "A",
        "l": 2603,
        "w": 52,
        "e1": {
          "n": "17",
          "h": 169,
          "o": 203
        },
        "e2": {
          "n": "35",
          "h": 349,
          "o": 190
        }
      },
      {
        "s": "G",
        "l": 2231,
        "w": 147,
        "e1": {
          "n": "09",
          "h": 89
        },
        "e2": {
          "n": "27",
          "h": 269
        }
      }
    ]
  },
  "Y88": {
    "e": 866,
    "n": "Green Lake",
    "mv": -6.06,
    "c": "Interlochen",
    "freqs": [
      {
        "t": "MC",
        "f": 122.9,
        "n": "GREENLAKE"
      },
      {
        "t": "CTAF",
        "f": 122.9,
        "n": "GREENLAKE"
      }
    ],
    "runways": [
      {
        "s": "G",
        "l": 2807,
        "w": 170,
        "e1": {
          "n": "24",
          "h": 235
        },
        "e2": {
          "n": "06",
          "h": 55
        }
      },
      {
        "s": "G",
        "l": 1523,
        "w": 176,
        "e1": {
          "n": "17",
          "h": 171
        },
        "e2": {
          "n": "35",
          "h": 351,
          "c": true
        }
      }
    ]
  },
  "Y89": {
    "e": 1030,
    "n": "Kalkaska City",
    "mv": -6.24,
    "c": "Kalkaska",
    "freqs": [
      {
        "t": "MC",
        "f": 122.9,
        "n": "KALKASKACITY"
      },
      {
        "t": "CTAF",
        "f": 122.9,
        "n": "KALKASKACITY"
      }
    ],
    "runways": [
      {
        "s": "A",
        "l": 3497,
        "w": 74,
        "e1": {
          "n": "10",
          "h": 108
        },
        "e2": {
          "n": "28",
          "h": 288
        }
      }
    ]
  },
  "Y83": {
    "e": 774,
    "n": "Sandusky City",
    "mv": -8.14,
    "c": "Sandusky",
    "freqs": [
      {
        "t": "UC",
        "f": 122.8,
        "n": "SANDUSKYCITY"
      },
      {
        "t": "CTAF",
        "f": 122.8,
        "n": "SANDUSKYCITY"
      }
    ],
    "runways": [
      {
        "s": "A",
        "l": 3461,
        "w": 75,
        "e1": {
          "n": "09",
          "h": 97
        },
        "e2": {
          "n": "27",
          "h": 277
        }
      },
      {
        "s": "G",
        "l": 2285,
        "w": 151,
        "e1": {
          "n": "18",
          "h": 187
        },
        "e2": {
          "n": "36",
          "h": 367
        }
      }
    ]
  }
}