{
  "TBPB": {
    "e": 164,
    "n": "Grantley Adams Intl",
    "mv": -15.75,
    "c": "Barbados",
    "freqs": [
      {
        "t": "A",
        "f": 129.35,
        "n": "ADAMS"
      },
      {
        "t": "A",
        "f": 120.7,
        "n": "ADAMS"
      },
      {
        "t": "A",
        "f": 128.85,
        "n": "ADAMS"
      },
      {
        "t": "ATIS",
        "f": 132.725,
        "n": "TBPB"
      },
      {
        "t": "D",
        "f": 120.7,
        "n": "ADAMS"
      },
      {
        "t": "D",
        "f": 128.85,
        "n": "ADAMS"
      },
      {
        "t": "G",
        "f": 121.9,
        "n": "ADAMS"
      },
      {
        "t": "T",
        "f": 118.7,
        "n": "ADAMS"
      }
    ],
    "runways": [
      {
        "s": "B",
        "l": 10999,
        "w": 136,
        "e1": {
          "n": "27",
          "h": 272
        },
        "e2": {
          "n": "09",
          "h": 92
        }
      }
    ]
  },
  "TBE": {
    "e": 48,
    "n": "Timbunke Airport",
    "mv": 4.05,
    "c": "Angoram",
    "runways": [
      {
        "s": "G",
        "l": 2458,
        "w": 82,
        "e1": {
          "n": "12",
          "h": 119
        },
        "e2": {
          "n": "30",
          "h": 299
        }
      }
    ]
  },
  "TBQ": {
    "e": 6077,
    "n": "Tarabo Airport",
    "mv": 4.91,
    "c": "Kainantu",
    "runways": [
      {
        "s": "G",
        "l": 2285,
        "w": 135,
        "e1": {
          "n": "07",
          "h": 69
        },
        "e2": {
          "n": "25",
          "h": 249
        }
      }
    ]
  },
  "TBV": {
    "e": 23,
    "n": "Tabal Airstrip",
    "mv": 8.4,
    "c": "Aur",
    "runways": [
      {
        "s": "D",
        "l": 3020,
        "w": 54,
        "e1": {
          "n": "04",
          "h": 38
        },
        "e2": {
          "n": "22",
          "h": 218
        }
      }
    ]
  }
}