{
  "S88": {
    "e": 1002,
    "n": "Skykomish State",
    "mv": 15.3,
    "c": "Skykomish",
    "freqs": [
      {
        "t": "MC",
        "f": 122.9,
        "n": "SKYKOMISHSTATE"
      },
      {
        "t": "CTAF",
        "f": 122.9,
        "n": "SKYKOMISHSTATE"
      }
    ],
    "runways": [
      {
        "s": "D",
        "l": 2142,
        "w": 186,
        "e1": {
          "n": "06",
          "h": 64
        },
        "e2": {
          "n": "24",
          "h": 244
        }
      }
    ]
  },
  "S84": {
    "e": 3474,
    "n": "Cottonwood Mun",
    "mv": 13.71,
    "c": "Cottonwood",
    "freqs": [
      {
        "t": "FSS",
        "f": 122.35,
        "n": "BOISE"
      },
      {
        "t": "MC",
        "f": 122.9,
        "n": "COTTONWOODMUN"
      },
      {
        "t": "CTAF",
        "f": 122.9,
        "n": "COTTONWOODMUN"
      }
    ],
    "runways": [
      {
        "s": "A",
        "l": 3191,
        "w": 50,
        "e1": {
          "n": "25",
          "h": 253
        },
        "e2": {
          "n": "07",
          "h": 73
        }
      }
    ]
  },
  "S89": {
    "e": 3805,
    "n": "Craigmont Mun",
    "mv": 13.71,
    "c": "Craigmont",
    "freqs": [
      {
        "t": "MC",
        "f": 122.9,
        "n": "CRAIGMONTMUN"
      },
      {
        "t": "CTAF",
        "f": 122.9,
        "n": "CRAIGMONTMUN"
      }
    ],
    "runways": [
      {
        "s": "A",
        "l": 2908,
        "w": 47,
        "e1": {
          "n": "25",
          "h": 254,
          "o": 278
        },
        "e2": {
          "n": "07",
          "h": 74
        }
      }
    ]
  },
  "S83": {
    "e": 2218,
    "n": "Shoshone Co",
    "mv": 13.97,
    "c": "Kellogg",
    "freqs": [
      {
        "t": "UC",
        "f": 122.8,
        "n": "SHOSHONECO"
      },
      {
        "t": "CTAF",
        "f": 122.8,
        "n": "SHOSHONECO"
      }
    ],
    "runways": [
      {
        "s": "A",
        "l": 5310,
        "w": 75,
        "e1": {
          "n": "25",
          "h": 255,
          "o": 331
        },
        "e2": {
          "n": "07",
          "h": 75
        }
      }
    ]
  },
  "S82": {
    "e": 1263,
    "n": "Kooskia Mun",
    "mv": 13.24,
    "c": "Kooskia",
    "freqs": [
      {
        "t": "MC",
        "f": 122.9,
        "n": "KOOSKIAMUN"
      },
      {
        "t": "CTAF",
        "f": 122.9,
        "n": "KOOSKIAMUN"
      }
    ],
    "runways": [
      {
        "s": "G",
        "l": 1941,
        "w": 51,
        "e1": {
          "n": "15",
          "h": 153
        },
        "e2": {
          "n": "33",
          "h": 333
        }
      }
    ]
  },
  "S85": {
    "e": 1943,
    "n": "Big Sky",
    "mv": 8.35,
    "c": "Culbertson",
    "freqs": [
      {
        "t": "UC",
        "f": 122.8,
        "n": "BIGSKY"
      },
      {
        "t": "CTAF",
        "f": 122.8,
        "n": "BIGSKY"
      }
    ],
    "runways": [
      {
        "s": "A",
        "l": 3776,
        "w": 56,
        "e1": {
          "n": "08",
          "h": 82
        },
        "e2": {
          "n": "26",
          "h": 262
        }
      }
    ]
  },
  "S87": {
    "e": 2115,
    "n": "Weiser Mun",
    "mv": 13.2,
    "c": "Weiser",
    "freqs": [
      {
        "t": "UC",
        "f": 122.8,
        "n": "WEISERMUN"
      },
      {
        "t": "CTAF",
        "f": 122.8,
        "n": "WEISERMUN"
      }
    ],
    "runways": [
      {
        "s": "A",
        "l": 3962,
        "w": 55,
        "e1": {
          "n": "12",
          "h": 123
        },
        "e2": {
          "n": "30",
          "h": 303
        }
      }
    ]
  },
  "S81": {
    "e": 4702,
    "n": "Indian Creek USFS",
    "mv": 13.02,
    "c": "Indian Creek",
    "freqs": [
      {
        "t": "MC",
        "f": 122.9,
        "n": "INDIANCREEKUSFS"
      },
      {
        "t": "CTAF",
        "f": 122.9,
        "n": "INDIANCREEKUSFS"
      }
    ],
    "runways": [
      {
        "s": "D",
        "l": 4599,
        "w": 30,
        "e1": {
          "n": "04",
          "h": 42
        },
        "e2": {
          "n": "22",
          "h": 222
        }
      }
    ]
  }
}