{
  "SYMR": {
    "e": 249,
    "n": "Matthews Ridge Airport",
    "mv": -15.71,
    "c": "Mabaruma",
    "runways": [
      {
        "s": "D",
        "l": 4709,
        "w": 33,
        "e1": {
          "n": "27",
          "h": 272
        },
        "e2": {
          "n": "09",
          "h": 92
        }
      }
    ]
  },
  "SYIB": {
    "e": 1650,
    "n": "Imbaimadai",
    "mv": -15.83,
    "runways": [
      {
        "s": "B",
        "l": 3002,
        "w": 38,
        "e1": {
          "n": "07",
          "h": 66
        },
        "e2": {
          "n": "25",
          "h": 246
        }
      }
    ]
  },
  "SYOR": {
    "e": 1801,
    "n": "Orinduik",
    "mv": -15.93,
    "runways": [
      {
        "s": "A",
        "l": 2465,
        "w": 40,
        "e1": {
          "n": "05",
          "h": 53
        },
        "e2": {
          "n": "23",
          "h": 233
        }
      }
    ]
  },
  "SYAR": {
    "e": 46,
    "n": "Anna Regina Airport",
    "mv": -16.42,
    "c": "Anna Regina",
    "runways": [
      {
        "s": "D",
        "l": 2367,
        "w": 87,
        "e1": {
          "n": "26",
          "h": 258
        },
        "e2": {
          "n": "08",
          "h": 78
        }
      }
    ]
  },
  "SYCJ": {
    "e": 76,
    "n": "Cheddi Jagan Intl",
    "mv": -16.55,
    "c": "Georgetown",
    "freqs": [
      {
        "t": "A",
        "f": 118.3,
        "n": "TIMEHRI"
      },
      {
        "t": "A",
        "f": 119.4,
        "n": "TIMEHRI"
      },
      {
        "t": "G",
        "f": 121.7,
        "n": "TIMEHRI"
      },
      {
        "t": "T",
        "f": 118.3,
        "n": "TIMEHRI"
      },
      {
        "t": "T",
        "f": 119.4,
        "n": "TIMEHRI"
      }
    ],
    "runways": [
      {
        "s": "B",
        "l": 7428,
        "w": 142,
        "e1": {
          "n": "06",
          "h": 61
        },
        "e2": {
          "n": "24",
          "h": 241
        }
      },
      {
        "s": "B",
        "l": 4996,
        "w": 141,
        "e1": {
          "n": "29",
          "h": 287
        },
        "e2": {
          "n": "11",
          "h": 107
        }
      }
    ]
  },
  "SYBT": {
    "e": 151,
    "n": "Bartica A Airport",
    "mv": -16.58,
    "c": "Bartica",
    "runways": [
      {
        "s": "A",
        "l": 2535,
        "w": 35,
        "e1": {
          "n": "24",
          "h": 235
        },
        "e2": {
          "n": "06",
          "h": 55
        }
      }
    ]
  },
  "SYNA": {
    "e": 12,
    "n": "New Amsterdam Airport",
    "mv": -16.92,
    "c": "New Amsterdam",
    "runways": [
      {
        "s": "CE",
        "l": 2587,
        "w": 44,
        "e1": {
          "n": "08",
          "h": 84
        },
        "e2": {
          "n": "26",
          "h": 264
        }
      }
    ]
  },
  "SYRO": {
    "e": 6,
    "n": "Rosignol Airport",
    "mv": -16.93,
    "c": "Rosignol",
    "runways": [
      {
        "s": "G",
        "l": 1514,
        "w": 37,
        "e1": {
          "n": "22",
          "h": 218
        },
        "e2": {
          "n": "04",
          "h": 38
        }
      }
    ]
  },
  "SYMD": {
    "e": 276,
    "n": "Mahdia",
    "mv": -16.18,
    "runways": [
      {
        "s": "A",
        "l": 2739,
        "w": 47,
        "e1": {
          "n": "17",
          "h": 170
        },
        "e2": {
          "n": "35",
          "h": 350
        }
      }
    ]
  },
  "SYKZ": {
    "e": 173,
    "n": "Konawaruk Airport",
    "mv": -16.73,
    "c": "Mahdia",
    "runways": [
      {
        "s": "D",
        "l": 3285,
        "w": 78,
        "e1": {
          "n": "13",
          "h": 134
        },
        "e2": {
          "n": "31",
          "h": 314
        }
      }
    ]
  },
  "SYKT": {
    "e": 2230,
    "n": "Kato",
    "mv": -16.24,
    "runways": [
      {
        "s": "G",
        "l": 2894,
        "w": 82,
        "e1": {
          "n": "26",
          "h": 255
        },
        "e2": {
          "n": "08",
          "h": 75
        }
      }
    ]
  },
  "SYPM": {
    "e": 2799,
    "n": "Paramakatoi Airport",
    "mv": -16.24,
    "c": "Mahdia",
    "runways": [
      {
        "s": "A",
        "l": 1798,
        "w": 58,
        "e1": {
          "n": "08",
          "h": 80
        },
        "e2": {
          "n": "26",
          "h": 260
        }
      }
    ]
  },
  "SYAN": {
    "e": 276,
    "n": "Annai",
    "mv": -16.46,
    "runways": [
      {
        "s": "D",
        "l": 3057,
        "w": 45,
        "e1": {
          "n": "07",
          "h": 65
        },
        "e2": {
          "n": "25",
          "h": 245
        }
      }
    ]
  },
  "SYKR": {
    "e": 302,
    "n": "Karanambo",
    "mv": -16.36,
    "runways": [
      {
        "s": "G",
        "l": 1107,
        "w": 28,
        "e1": {
          "n": "06",
          "h": 59
        },
        "e2": {
          "n": "24",
          "h": 239
        }
      }
    ]
  },
  "SYLH": {
    "e": 271,
    "n": "Lethem Airport",
    "mv": -16.31,
    "c": "Lethem",
    "runways": [
      {
        "s": "G",
        "l": 4543,
        "w": 79,
        "e1": {
          "n": "27",
          "h": 266
        },
        "e2": {
          "n": "09",
          "h": 86
        }
      }
    ]
  },
  "SYAP": {
    "e": 305,
    "n": "Apoteri",
    "mv": -16.76,
    "runways": [
      {
        "s": "G",
        "l": 1932,
        "w": 75,
        "e1": {
          "n": "06",
          "h": 63
        },
        "e2": {
          "n": "24",
          "h": 243
        }
      }
    ]
  },
  "SYLT": {
    "e": 351,
    "n": "Lethem",
    "mv": -16.38,
    "runways": [
      {
        "s": "A",
        "l": 5953,
        "w": 101,
        "e1": {
          "n": "07",
          "h": 74
        },
        "e2": {
          "n": "25",
          "h": 254
        }
      }
    ]
  },
  "SYMP": {
    "e": 400,
    "n": "Mountain Point",
    "mv": -16.3,
    "c": "Mountain Point Guyana",
    "runways": [
      {
        "s": "G",
        "l": 5874,
        "w": 205,
        "e1": {
          "n": "27",
          "h": 269
        },
        "e2": {
          "n": "09",
          "h": 89
        }
      }
    ]
  },
  "SYDW": {
    "e": 400,
    "n": "Dadanawa Airport",
    "mv": -16.36,
    "c": "Lethem",
    "runways": [
      {
        "s": "G",
        "l": 1844,
        "w": 40,
        "e1": {
          "n": "09",
          "h": 91
        },
        "e2": {
          "n": "27",
          "h": 271
        }
      }
    ]
  },
  "SYLE": {
    "e": 424,
    "n": "Amatopo Airstrip",
    "mv": -17.14,
    "c": "Lethem",
    "runways": [
      {
        "s": "D",
        "l": 1926,
        "w": 13,
        "e1": {
          "n": "12",
          "h": 116
        },
        "e2": {
          "n": "30",
          "h": 296
        }
      }
    ]
  },
  "SYAH": {
    "e": 591,
    "n": "Aishalton",
    "mv": -16.38,
    "runways": [
      {
        "s": "G",
        "l": 1652,
        "w": 53,
        "e1": {
          "n": "24",
          "h": 236
        },
        "e2": {
          "n": "06",
          "h": 56
        }
      }
    ]
  },
  "SYLP": {
    "e": 551,
    "n": "Lumid Pau",
    "mv": -16.39,
    "runways": [
      {
        "s": "G",
        "l": 1818,
        "w": 50,
        "e1": {
          "n": "12",
          "h": 116
        },
        "e2": {
          "n": "30",
          "h": 296
        }
      }
    ]
  }
}